README.rst
setup.py
with_fixture/__init__.py
with_fixture/testcase.py
with_fixture.egg-info/PKG-INFO
with_fixture.egg-info/SOURCES.txt
with_fixture.egg-info/dependency_links.txt
with_fixture.egg-info/requires.txt
with_fixture.egg-info/top_level.txt