Metadata-Version: 1.0
Name: with-fixture
Version: 0.1
Summary: An experiment in using context-managers in unittest fixtures.
Home-page: http://github.com/abingham/with_fixture
Author: Austin Bingham
Author-email: austin.bingham@gmail.com
License: MIT
Keywords: testing
Platform: UNKNOWN
